smsocials/__init__.py
smsocials/clients/base.py
smsocials/clients/vk.py
smsocials/services/vk.py
smsocials-0.4.0.dist-info/METADATA
smsocials-0.4.0.dist-info/WHEEL
smsocials-0.4.0.dist-info/RECORD
