Metadata-Version: 2.1
Name: smsocials
Version: 0.4.0
Summary: Work with social networks
Author: Artemy Sh
Author-email: artemy.sh@gmail.com
Requires-Python: >=3.12,<4.0
Classifier: Programming Language :: Python :: 3
Classifier: Programming Language :: Python :: 3.12
Classifier: Programming Language :: Python :: 3.13
Requires-Dist: aiofiles (>=24.1.0,<25.0.0)
Requires-Dist: aiohttp (>=3.11.10,<4.0.0)
